QuickDataFlow/__init__.py
QuickDataFlow/shm_message.py
QuickDataFlow/build/libQuickDataFlow.so
QuickDataFlow-2.1.2.dist-info/LICENSE.txt
QuickDataFlow-2.1.2.dist-info/METADATA
QuickDataFlow-2.1.2.dist-info/WHEEL
QuickDataFlow-2.1.2.dist-info/top_level.txt
QuickDataFlow-2.1.2.dist-info/RECORD
