Metadata-Version: 2.1
Name: QuickDataFlow
Version: 2.1.2
Summary: QuickDataFlow library is designed for messaging between programs written in c++ and python
Home-page: https://github.com/ilyajob05/QuickDataFlow
Author: ilyajob05
License: MIT
Keywords: DataFlow,cpp,c++,IPC,shared memory
Platform: manylinux2014_x86_64
Classifier: Topic :: Utilities
Classifier: Programming Language :: Python
Classifier: Programming Language :: Python :: 3
Classifier: Programming Language :: Python :: 3 :: Only
Classifier: Environment :: Other Environment
Classifier: Intended Audience :: Developers
Classifier: License :: OSI Approved :: MIT License
Classifier: Topic :: Software Development :: Libraries :: Python Modules
Classifier: Operating System :: POSIX :: Linux
Classifier: Operating System :: Unix
License-File: LICENSE.txt
